epigeec/_version.py
epigeec/__init__.py
epigeec/bin/bw_to_hdf5
epigeec/bin/correlation_w_nm
epigeec/bin/correlation
epigeec/bin/correlation_w
epigeec/bin/bg_to_hdf5
epigeec/bin/filter
epigeec/bin/correlation_nm
epigeec/python/__init__.py
epigeec/python/core/config.py
epigeec/python/core/error.py
epigeec/python/core/make_matrix.py
epigeec/python/core/validators.py
epigeec/python/core/__init__.py
epigeec/python/core/input_parser.py
epigeec/python/core/utils.py
epigeec/python/core/launcher.py
epigeec/python/core/main.py
epigeec/.dylibs/libbwreader.dylib
epigeec/.dylibs/libhdf5.310.5.1.dylib
epigeec/.dylibs/libaec.0.1.4.dylib
epigeec/.dylibs/libboost_iostreams.dylib
epigeec/.dylibs/libicudata.77.1.dylib
epigeec/.dylibs/libicuuc.77.1.dylib
epigeec/.dylibs/libomp.dylib
epigeec/.dylibs/libboost_random.dylib
epigeec/.dylibs/libboost_regex.dylib
epigeec/.dylibs/libsz.2.0.1.dylib
epigeec/.dylibs/libcore.dylib
epigeec/.dylibs/libhdf5_hl.310.0.6.dylib
epigeec/.dylibs/libboost_filesystem.dylib
epigeec/.dylibs/liblzma.5.dylib
epigeec/.dylibs/libboost_atomic.dylib
epigeec/.dylibs/libicui18n.77.1.dylib
epigeec/.dylibs/libzstd.1.5.7.dylib
epigeec-1.6.2.dist-info/RECORD
epigeec-1.6.2.dist-info/LICENSE
epigeec-1.6.2.dist-info/WHEEL
epigeec-1.6.2.dist-info/entry_points.txt
epigeec-1.6.2.dist-info/top_level.txt
epigeec-1.6.2.dist-info/METADATA
