Metadata-Version: 2.2
Name: epigeec
Version: 1.6.2
Summary: Tools for fast NxN correlation of whole-genome epigenomic data.
Author-email: Jonathan Laperle <jonathan.laperle@usherbrooke.ca>
License: GPL-3.0-or-later
Requires-Python: >=3.10
License-File: LICENSE
Requires-Dist: pandas
Requires-Dist: numpy
Requires-Dist: h5py
Requires-Dist: future
Provides-Extra: test
Requires-Dist: pytest; extra == "test"
Requires-Dist: pyBigWig; extra == "test"
Requires-Dist: pytest-json-ctrf; extra == "test"
Provides-Extra: dev
Requires-Dist: epigeec[test]; extra == "dev"
